simple_print/__init__.py
simple_print/consts.py
simple_print/spprint.py
simple_print/sprint.py
simple_print/sprint_err.py
simple_print-2.2.7.dist-info/licenses/LICENSE
simple_print-2.2.7.dist-info/METADATA
simple_print-2.2.7.dist-info/WHEEL
simple_print-2.2.7.dist-info/top_level.txt
simple_print-2.2.7.dist-info/RECORD
