Metadata-Version: 2.4
Name: simple-print
Version: 2.2.7
Summary: Local development tool for logs printing.
Home-page: https://github.com/Sobolev5/simple-print/
Author: Sobolev Andrey
Author-email: Sobolev Andrey <email.asobolev@gmail.com>
Requires-Python: >=3.12
License-File: LICENSE
Requires-Dist: executing==2.2.1
Requires-Dist: asttokens==3.0.1
Dynamic: author
Dynamic: home-page
Dynamic: license-file
Dynamic: requires-python
